MANIFEST.in
requirements.txt
setup.py
MotionArtifactRemoval/__init__.py
MotionArtifactRemoval.egg-info/PKG-INFO
MotionArtifactRemoval.egg-info/SOURCES.txt
MotionArtifactRemoval.egg-info/dependency_links.txt
MotionArtifactRemoval.egg-info/requires.txt
MotionArtifactRemoval.egg-info/top_level.txt
MotionArtifactRemoval/mmar/__init__.py
MotionArtifactRemoval/mmar/command_line_params.py
MotionArtifactRemoval/mmar/create_mask.py
MotionArtifactRemoval/mmar/message_log.py
MotionArtifactRemoval/mmar/mmar.py
MotionArtifactRemoval/mmar/process_slice.py
MotionArtifactRemoval/mmar/version.py
MotionArtifactRemoval/mmar/write_output.py
MotionArtifactRemoval/mmar_gui/__init__.py
MotionArtifactRemoval/mmar_gui/gui.py
MotionArtifactRemoval/motion_detector/__init__.py
MotionArtifactRemoval/motion_detector/run.py
MotionArtifactRemoval/motion_detector/train.py
MotionArtifactRemoval/motion_detector/utils.py
MotionArtifactRemoval/ssUNET/__init__.py
MotionArtifactRemoval/ssUNET/dataset.py
MotionArtifactRemoval/ssUNET/generate_output.py
MotionArtifactRemoval/ssUNET/loss.py
MotionArtifactRemoval/ssUNET/metrics.py
MotionArtifactRemoval/ssUNET/results.py
MotionArtifactRemoval/ssUNET/test_load_data.py
MotionArtifactRemoval/ssUNET/train.py
MotionArtifactRemoval/ssUNET/utils.py
MotionArtifactRemoval/ssUNET/weights/dti.pth