Metadata-Version: 2.1
Name: MotionArtifactRemoval
Version: 1.0.26
Summary: Motion Artifact Removal
Home-page: https://www.jax.org
Author: Jim Peterson, Abed Ghanbari
Author-email: abed.ghanbari@jax.org
License: BSD 2-clause
Platform: UNKNOWN
Classifier: Development Status :: 1 - Planning
Classifier: Intended Audience :: Science/Research
Classifier: License :: OSI Approved :: BSD License
Classifier: Operating System :: POSIX :: Linux
Classifier: Programming Language :: Python :: 2
Classifier: Programming Language :: Python :: 2.7
Classifier: Programming Language :: Python :: 3
Classifier: Programming Language :: Python :: 3.4
Classifier: Programming Language :: Python :: 3.5
